README
setup.py
/home/alejandro/python/PyQt/Qtumblr/qtumblr/__init__.py
/home/alejandro/python/PyQt/Qtumblr/qtumblr/audio.py
/home/alejandro/python/PyQt/Qtumblr/qtumblr/chat.py
/home/alejandro/python/PyQt/Qtumblr/qtumblr/dashboard.py
/home/alejandro/python/PyQt/Qtumblr/qtumblr/link.py
/home/alejandro/python/PyQt/Qtumblr/qtumblr/photo.py
/home/alejandro/python/PyQt/Qtumblr/qtumblr/qtumblr-client.py
/home/alejandro/python/PyQt/Qtumblr/qtumblr/quote.py
/home/alejandro/python/PyQt/Qtumblr/qtumblr/text.py
/home/alejandro/python/PyQt/Qtumblr/qtumblr/tumblr.py
/home/alejandro/python/PyQt/Qtumblr/qtumblr/video.py
/home/alejandro/python/PyQt/Qtumblr/qtumblr/gui/__init__.py
/home/alejandro/python/PyQt/Qtumblr/qtumblr/gui/advancedoptions.py
/home/alejandro/python/PyQt/Qtumblr/qtumblr/gui/audio_ui.py
/home/alejandro/python/PyQt/Qtumblr/qtumblr/gui/chat_ui.py
/home/alejandro/python/PyQt/Qtumblr/qtumblr/gui/dashboard_ui.py
/home/alejandro/python/PyQt/Qtumblr/qtumblr/gui/link_ui.py
/home/alejandro/python/PyQt/Qtumblr/qtumblr/gui/main_ui.py
/home/alejandro/python/PyQt/Qtumblr/qtumblr/gui/photo_ui.py
/home/alejandro/python/PyQt/Qtumblr/qtumblr/gui/quote_ui.py
/home/alejandro/python/PyQt/Qtumblr/qtumblr/gui/text_ui.py
/home/alejandro/python/PyQt/Qtumblr/qtumblr/gui/video_ui.py
/media/Respaldo/python/PyQt/Qtumblr/qtumblr/__init__.py
/media/Respaldo/python/PyQt/Qtumblr/qtumblr/audio.py
/media/Respaldo/python/PyQt/Qtumblr/qtumblr/chat.py
/media/Respaldo/python/PyQt/Qtumblr/qtumblr/dashboard.py
/media/Respaldo/python/PyQt/Qtumblr/qtumblr/link.py
/media/Respaldo/python/PyQt/Qtumblr/qtumblr/photo.py
/media/Respaldo/python/PyQt/Qtumblr/qtumblr/qtumblr-client.py
/media/Respaldo/python/PyQt/Qtumblr/qtumblr/quote.py
/media/Respaldo/python/PyQt/Qtumblr/qtumblr/text.py
/media/Respaldo/python/PyQt/Qtumblr/qtumblr/tumblr.py
/media/Respaldo/python/PyQt/Qtumblr/qtumblr/video.py
/media/Respaldo/python/PyQt/Qtumblr/qtumblr/gui/__init__.py
Qtumblr.egg-info/PKG-INFO
Qtumblr.egg-info/SOURCES.txt
Qtumblr.egg-info/dependency_links.txt
Qtumblr.egg-info/requires.txt
Qtumblr.egg-info/top_level.txt
