Metadata-Version: 1.0
Name: Qtumblr
Version: 0.1
Summary: Qt Tumblr Client based on Opentumblr
Home-page: http://ialex.org
Author: Alejandro Villanueva
Author-email: admin at ialex.org
License: MIT
Platform: UNKNOWN
